setup.py
setup.sh
setup_gip.py
ez_setup/README.txt
ez_setup/__init__.py
src/OSG_Gratia_Viewer.egg-info/PKG-INFO
src/OSG_Gratia_Viewer.egg-info/SOURCES.txt
src/OSG_Gratia_Viewer.egg-info/dependency_links.txt
src/OSG_Gratia_Viewer.egg-info/entry_points.txt
src/OSG_Gratia_Viewer.egg-info/namespace_packages.txt
src/OSG_Gratia_Viewer.egg-info/requires.txt
src/OSG_Gratia_Viewer.egg-info/top_level.txt
src/gratia/__init__.py
src/gratia/config/DBSecurity.xml
src/gratia/config/__init__.py
src/gratia/config/development.conf
src/gratia/config/generic_queries.xml
src/gratia/config/gip.conf
src/gratia/config/gratia_bar_queries.xml
src/gratia/config/gratia_cumulative_queries.xml
src/gratia/config/gratia_graphs.xml
src/gratia/config/gratia_pie_queries.xml
src/gratia/config/gratia_site_queries.xml
src/gratia/config/gratia_user_queries.xml
src/gratia/config/gratia_vo_queries.xml
src/gratia/config/gridscan_queries.xml
src/gratia/config/matplotlibrc
src/gratia/config/osg_logo_4c_white.png
src/gratia/config/osg_logo_4c_white.tif
src/gratia/config/prod.conf
src/gratia/config/security.xml
src/gratia/config/static_generator.cfg
src/gratia/config/text_queries.xml
src/gratia/config/vo_ownership_queries.xml
src/gratia/config/website-devel.xml
src/gratia/config/website.xml
src/gratia/database/__init__.py
src/gratia/database/query_handler.py
src/gratia/gip/__init__.py
src/gratia/gip/analysis.py
src/gratia/gip/common.py
src/gratia/gip/ldap.py
src/gratia/graphs/__init__.py
src/gratia/graphs/animated_thumbnail.py
src/gratia/graphs/gratia_graphs.py
src/gratia/tools/__init__.py
src/gratia/tools/gip_count.py
src/gratia/tools/gip_record.py
src/gratia/tools/gratia_web.py
src/gratia/tools/gratia_web_dev.py
src/gratia/tools/gridscan_download.py
src/gratia/tools/site_normalization.py
src/gratia/tools/static_graphs.py
src/gratia/web/__init__.py
templates/focus.tmpl
templates/image_map.tmpl
templates/main.tmpl
templates/overview.tmpl
templates/refine.tmpl
templates/site.tmpl
templates/user.tmpl
templates/vo.tmpl
templates/vo_exitcode.tmpl
templates/vo_opp.tmpl
templates/vo_opp2.tmpl
templates/vo_overview.tmpl
