Metadata-Version: 1.0
Name: OSG-Gratia-Viewer
Version: 0.1
Summary: Python-based Gratia Viewer.
Home-page: http://t2.unl.edu/documentation/gratia_graphs
Author: Brian Bockelman
Author-email: bbockelm@math.unl.edu
License: UNKNOWN
Platform: UNKNOWN
Classifier: Development Status :: 2 - Pre-Alpha
Classifier: Intended Audience :: Developers
Classifier: Programming Language :: Python
Classifier: Natural Language :: English
Classifier: Operating System :: POSIX
